pyqtapplicationhelper/__init__.py
pyqtapplicationhelper/change_log_dialog.py
pyqtapplicationhelper/inherits_ui_file.py
pyqtapplicationhelper-0.1.13.dist-info/LICENSE
pyqtapplicationhelper-0.1.13.dist-info/WHEEL
pyqtapplicationhelper-0.1.13.dist-info/METADATA
pyqtapplicationhelper-0.1.13.dist-info/RECORD
