Metadata-Version: 2.1
Name: pyqtapplicationhelper
Version: 0.1.13
Summary: Adds helpfule tools for pyqt apps
Author: michaeldcanady
Requires-Python: >3.8.0
Classifier: License :: OSI Approved :: MIT License
Requires-Dist: Markdown==3.4.1
Requires-Dist: PyQt6==6.3.1
Requires-Dist: PyQt6-Qt6==6.3.1
Requires-Dist: PyQt6-sip==13.4.0
Project-URL: homepage, https://github.com/michaeldcanady/pyqtapplicationhelper#readme
Project-URL: repository, https://github.com/michaeldcanady/pyqtapplicationhelper
